python_utils_AndrewGarwood/__init__.py
python_utils_AndrewGarwood/file.py
python_utils_AndrewGarwood/io.py
python_utils_AndrewGarwood/pd_utils.py
python_utils_AndrewGarwood/regex.py
python_utils_AndrewGarwood/config/env.py
python_utils_AndrewGarwood/objects/FieldCondition.py
python_utils_andrewgarwood-0.0.2.dist-info/licenses/LICENSE
python_utils_andrewgarwood-0.0.2.dist-info/METADATA
python_utils_andrewgarwood-0.0.2.dist-info/WHEEL
python_utils_andrewgarwood-0.0.2.dist-info/top_level.txt
python_utils_andrewgarwood-0.0.2.dist-info/RECORD
