Metadata-Version: 2.4
Name: python_utils_AndrewGarwood
Version: 0.0.2
Summary: A collection of python scripts that are used to automate work tasks.
Author-email: Andrew Garwood <andrew.garwood.949@gmail.com>
License: Copyright (c) 2018 The Python Packaging Authority
Project-URL: Homepage, https://github.com/AndrewGarwood/python_utils_AndrewGarwood
Project-URL: Issues, https://github.com/AndrewGarwood/python_utils_AndrewGarwood/issues
License-File: LICENSE
Requires-Dist: pandas
Requires-Dist: openpyxl
Dynamic: license-file
